setup.py
mp4file/__init__.py
mp4file/atom.py
mp4file/atomsearch.py
mp4file/atomsearch_test.py
mp4file/mp4file.py
mp4file.egg-info/PKG-INFO
mp4file.egg-info/SOURCES.txt
mp4file.egg-info/dependency_links.txt
mp4file.egg-info/top_level.txt